invenio_sse/__init__.py
invenio_sse/cli.py
invenio_sse/config.py
invenio_sse/ext.py
invenio_sse/proxies.py
invenio_sse/utils.py
invenio_sse/version.py
invenio_sse/contrib/__init__.py
invenio_sse/contrib/deposit/__init__.py
invenio_sse/contrib/deposit/ext.py
invenio_sse/contrib/deposit/rest.py
invenio_sse-1.0.0a2.dist-info/top_level.txt
invenio_sse-1.0.0a2.dist-info/entry_points.txt
invenio_sse-1.0.0a2.dist-info/METADATA
invenio_sse-1.0.0a2.dist-info/DESCRIPTION.rst
invenio_sse-1.0.0a2.dist-info/metadata.json
invenio_sse-1.0.0a2.dist-info/WHEEL
invenio_sse-1.0.0a2.dist-info/RECORD
