Metadata-Version: 2.0
Name: invenio-sse
Version: 1.0.0a2
Summary: Invenio module for HTML5 server-sent events support.
Home-page: https://github.com/inveniosoftware/invenio-sse
Author: CERN
Author-email: info@inveniosoftware.org
License: GPLv2
Keywords: invenio SSE
Platform: any
Classifier: Environment :: Web Environment
Classifier: Intended Audience :: Developers
Classifier: License :: OSI Approved :: GNU General Public License v2 (GPLv2)
Classifier: Operating System :: OS Independent
Classifier: Programming Language :: Python
Classifier: Topic :: Internet :: WWW/HTTP :: Dynamic Content
Classifier: Topic :: Software Development :: Libraries :: Python Modules
Classifier: Programming Language :: Python :: 2
Classifier: Programming Language :: Python :: 2.7
Classifier: Programming Language :: Python :: 3
Classifier: Programming Language :: Python :: 3.3
Classifier: Programming Language :: Python :: 3.4
Classifier: Programming Language :: Python :: 3.5
Classifier: Development Status :: 3 - Alpha
Requires-Dist: Flask (>=0.11.1)
Requires-Dist: redis (>=2.10.5)
Provides-Extra: all
Requires-Dist: Sphinx (>=1.5.1); extra == 'all'
Requires-Dist: check-manifest (>=0.25); extra == 'all'
Requires-Dist: coverage (>=4.0); extra == 'all'
Requires-Dist: invenio-accounts (>=1.0.0b3); extra == 'all'
Requires-Dist: invenio-access (>=1.0.0a11); extra == 'all'
Requires-Dist: invenio-rest[cors] (>=1.0.0a10); extra == 'all'
Requires-Dist: isort (>=4.2.2); extra == 'all'
Requires-Dist: mock (>=1.3.0); extra == 'all'
Requires-Dist: psycopg2 (>=2.6.1); extra == 'all'
Requires-Dist: pydocstyle (>=1.0.0); extra == 'all'
Requires-Dist: pytest-cache (>=1.0); extra == 'all'
Requires-Dist: pytest-cov (>=1.8.0); extra == 'all'
Requires-Dist: pytest-pep8 (>=1.0.6); extra == 'all'
Requires-Dist: pytest (>=2.8.0); extra == 'all'
Requires-Dist: invenio-deposit (>=1.0.0a8); extra == 'all'
Requires-Dist: Sphinx (>=1.5.1); extra == 'all'
Requires-Dist: check-manifest (>=0.25); extra == 'all'
Requires-Dist: coverage (>=4.0); extra == 'all'
Requires-Dist: invenio-accounts (>=1.0.0b3); extra == 'all'
Requires-Dist: invenio-access (>=1.0.0a11); extra == 'all'
Requires-Dist: invenio-rest[cors] (>=1.0.0a10); extra == 'all'
Requires-Dist: isort (>=4.2.2); extra == 'all'
Requires-Dist: mock (>=1.3.0); extra == 'all'
Requires-Dist: psycopg2 (>=2.6.1); extra == 'all'
Requires-Dist: pydocstyle (>=1.0.0); extra == 'all'
Requires-Dist: pytest-cache (>=1.0); extra == 'all'
Requires-Dist: pytest-cov (>=1.8.0); extra == 'all'
Requires-Dist: pytest-pep8 (>=1.0.6); extra == 'all'
Requires-Dist: pytest (>=2.8.0); extra == 'all'
Requires-Dist: invenio-deposit (>=1.0.0a8); extra == 'all'
Provides-Extra: deposit
Requires-Dist: invenio-deposit (>=1.0.0a8); extra == 'deposit'
Provides-Extra: docs
Requires-Dist: Sphinx (>=1.5.1); extra == 'docs'
Provides-Extra: tests
Requires-Dist: check-manifest (>=0.25); extra == 'tests'
Requires-Dist: coverage (>=4.0); extra == 'tests'
Requires-Dist: invenio-accounts (>=1.0.0b3); extra == 'tests'
Requires-Dist: invenio-access (>=1.0.0a11); extra == 'tests'
Requires-Dist: invenio-rest[cors] (>=1.0.0a10); extra == 'tests'
Requires-Dist: isort (>=4.2.2); extra == 'tests'
Requires-Dist: mock (>=1.3.0); extra == 'tests'
Requires-Dist: psycopg2 (>=2.6.1); extra == 'tests'
Requires-Dist: pydocstyle (>=1.0.0); extra == 'tests'
Requires-Dist: pytest-cache (>=1.0); extra == 'tests'
Requires-Dist: pytest-cov (>=1.8.0); extra == 'tests'
Requires-Dist: pytest-pep8 (>=1.0.6); extra == 'tests'
Requires-Dist: pytest (>=2.8.0); extra == 'tests'
